[{"opponentName":"Mumbai Indians","runs":"0","balls":"0","fours":"0","sixes":"0","sr":"0.00","date":" Nov 5 2020","venue":" Dubai","result":"Mum Indians won by 57 runs"},{"opponentName":"Kolkata Knight Riders","runs":"0","balls":"0","fours":"0","sixes":"0","sr":"0.00","date":" Oct 24 2020","venue":" Abu Dhabi","result":"KKR won by 59 runs"},{"opponentName":"Kings XI Punjab","runs":"3","balls":"1","fours":"0","sixes":"0","sr":"300.00","date":" Sep 20 2020","venue":" Dubai","result":"Match tied (Capitals won the one-over eliminator)"},{"opponentName":"Sunrisers Hyderabad","runs":"3","balls":"2","fours":"0","sixes":"0","sr":"150.00","date":" Sep 29 2020","venue":" Abu Dhabi","result":"Sunrisers won by 15 runs"}]